{
   "chapters" : [
      {
         "entries" : [
            {
               "author" : "frew_schmidt",
               "tags" : [],
               "text" : "Frew seems to be really persistent with this series. If you have missed the earlier once and especially if you don't know what is a Supervisor, start with <a href=\"https://blog.afoolishmanifesto.com/posts/supervisors-and-init-systems-1/\">part 1</a> and the check out the <a href=\"https://blog.afoolishmanifesto.com/tags/supervisors/\">list</a> of episodes.",
               "title" : "Supervisors and Init Systems: Part 6 and 7",
               "ts" : "2017.07.31",
               "url" : "https://blog.afoolishmanifesto.com/posts/supervisors-and-init-systems-6/"
            },
            {
               "author" : "dave_jacoby",
               "tags" : [],
               "text" : "Dave wants to know what documentation would *you* add to his code, but there are no comments. So do you think his code does not need any documentation or is documenting the need of documentation too META?",
               "title" : "Considering Code Documentation ",
               "ts" : "2017.08.02",
               "url" : "https://varlogrant.blogspot.com/2017/08/considering-code-documentation.html"
            },
            {
               "author" : "doug_bell",
               "tags" : [],
               "text" : "This is the first trial release after a big merge. Give some feedback!",
               "title" : "Log::Any - Now With Structured Logging",
               "ts" : "2017.08.03",
               "url" : "http://blogs.perl.org/users/preaction/2017/08/logany---now-with-structured-logging.html"
            }
         ],
         "title" : "Articles"
      },
      {
         "entries" : [
            {
               "author" : "",
               "tags" : [],
               "text" : "The code snippets of ActiveState have aged and now they would like you to improve them, but Johannes Kilian looked at the GitHub repository and found that it needs some administrative improvement as well.",
               "title" : "Code Recipes Now On Github - 5,000+ Recipes for Python, Perl, Ruby and More",
               "ts" : "2017.08.03",
               "url" : "https://www.activestate.com/blog/2017/08/code-recipes-now-github-5000-recipes-python-perl-ruby-and-more"
            }
         ],
         "title" : "Code"
      },
      {
         "entries" : [
            {
               "author" : "thomas_klausner",
               "tags" : [],
               "text" : "Thomas gives his view on what (Web) Framework should do and should not do. I hope we can make use of his views in building Bailador to be a useful framework that will drive people towards Perl 6.",
               "title" : "What I (domm) expect from a Web Framework",
               "ts" : "2017.08.04",
               "url" : "https://domm.plix.at/perl/2017_08_what_i_expect_from_a_web_framework.html"
            }
         ],
         "title" : "Web"
      },
      {
         "entries" : [
            {
               "author" : "david_farrell",
               "tags" : [],
               "text" : "",
               "title" : "What's new on CPAN - July 2017",
               "ts" : "2017.08.02",
               "url" : "http://perltricks.com/article/what-s-new-on-cpan---july-2017/"
            }
         ],
         "title" : "CPAN"
      },
      {
         "entries" : [
            {
               "author" : "lukas_mai",
               "tags" : [],
               "text" : "The <a href=\"http://wiki.c2.com/?FizzBuzzTest\">FizzBuzz Test</a> is a programming interview question designed to help  filter out the 99.5% of programming job candidates who can't seem to program their way out of a wet paper bag. I am not sure the original authors had this in their mind.... and the Aristotle golfed it. Creepy.",
               "title" : "/Fizz|Buzz/",
               "ts" : "2017.08.05",
               "url" : "http://blogs.perl.org/users/mauke/2017/08/fizzbuzz.html"
            }
         ],
         "title" : "Fun"
      },
      {
         "entries" : [
            {
               "author" : "",
               "tags" : [],
               "text" : "This is the grant of Jonathan Worthington.",
               "title" : "Grant Extension Approved: Perl 6 Performance and Reliability Engineering",
               "ts" : "2017.07.31",
               "url" : "http://news.perlfoundation.org/2017/07/grant-extension-approved-perl-.html"
            },
            {
               "author" : "will_coleda",
               "tags" : [],
               "text" : "This was published on 1st August with a dead-line of 5th August. Strange. It is also over by the time you read this message.",
               "title" : "Call for Grant Proposals (July 2017 Round)",
               "ts" : "2017.08.01",
               "url" : "http://news.perlfoundation.org/2017/08/call-for-grant-proposals-july-2.html"
            },
            {
               "author" : "will_coleda",
               "tags" : [],
               "text" : "A bit late, but the report is here.",
               "title" : "May 2017 Grant Votes",
               "ts" : "2017.08.31",
               "url" : "http://news.perlfoundation.org/2017/08/may-2017-grant-votes.html"
            },
            {
               "author" : "makoto_nozaki",
               "tags" : [],
               "text" : "",
               "title" : "Perl 5 Core Grant Approved: Zefram maintaining the Perl 5 Core",
               "ts" : "2017.08.01",
               "url" : "http://news.perlfoundation.org/2017/08/perl-5-core-grant-approved-zef.html"
            },
            {
               "author" : "makoto_nozaki",
               "tags" : [],
               "text" : "",
               "title" : "Grant Extension Approved: Dave Mitchell Perl 5 Core",
               "ts" : "2017.08.03",
               "url" : "http://news.perlfoundation.org/2017/08/grant-extension-approved-dave-.html"
            },
            {
               "author" : "",
               "tags" : [],
               "text" : "",
               "title" : "Maintaining Perl 5 (Tony Cook): Grant Report for May/June 2017",
               "ts" : "2017.08.04",
               "url" : "http://news.perlfoundation.org/2017/08/maintaining-perl-5-tony-cook-g.html"
            }
         ],
         "title" : "Grants"
      },
      {
         "entries" : [
            {
               "author" : "sawyer_x",
               "tags" : [],
               "text" : "",
               "title" : "Perl 5 Porters Mailing List Summary: July 24th-30th",
               "ts" : "2017.07.31",
               "url" : "http://blogs.perl.org/users/sawyer_x/2017/07/perl-5-porters-mailing-list-summary-july-24th-30th.html"
            },
            {
               "author" : "",
               "tags" : [],
               "text" : "Apparently the Strawberryperl domain has expired and the site was off-line for a few hours or maybe a whole day, but it is back online now. <a href=\"https://www.reddit.com/r/perl/comments/6qoj7p/strawberry_perl_site_is_down/\">report</a>",
               "title" : "Strawberry Perl",
               "ts" : "2017.07.31",
               "url" : "http://strawberryperl.com/"
            }
         ],
         "title" : "Perl 5"
      },
      {
         "entries" : [
            {
               "author" : "gabor_szabo",
               "tags" : [],
               "text" : "The <a href=\"http://modules.perl6.org/\">modules list of Perl 6</a> now show both the Travis-CI and Appveyor status of the modules where those are enabled. For the modules that the Continuous Integration is not running yet you can find a link explaining how to set that up. 2 Days ago Appveyor stood at 40. Today at 59. It is now your turn to help the Perl 6 modules run on Windows. UPDATE: The site was updated. It looks much better now, but I am not sure if you can easily find the modules that need help with Appveyor or Travis-CI configuration.",
               "title" : "Continuous Integration for Perl 6 modules",
               "ts" : "2017.07.30",
               "url" : "http://perl6maven.com/continuous-integration-for-perl6-modules"
            },
            {
               "author" : "liztormato",
               "tags" : [],
               "text" : "The 100th episode of the Perl 6 weekly blog post.",
               "title" : "2017.31 Moar Smaller",
               "ts" : "2017.07.31",
               "url" : "https://p6weekly.wordpress.com/2017/07/31/2017-31-moar-smaller/"
            },
            {
               "author" : "jonathan_worthington",
               "tags" : [],
               "text" : "If I understand it correctly, in a nutshell, this specialization, or in short spesh, is about stripping out late-binding and creating, well, specialized versions of it. But don't take my understanding. Read it yourself!",
               "title" : "MoarVM Specializer Improvements Part 1: Gathering Data",
               "ts" : "2017.08.06",
               "url" : "https://6guts.wordpress.com/2017/08/06/moarvm-specializer-improvements-part-1-gathering-data/"
            },
            {
               "author" : "aaronsherman",
               "tags" : [],
               "text" : "Just a code snippet",
               "title" : "If you ever want to explain Seq's to a Python programmer ",
               "ts" : "2017.07.27",
               "url" : "https://www.reddit.com/r/perl6/comments/6q51g7/if_you_ever_want_to_explain_seqs_to_a_python/"
            },
            {
               "author" : "",
               "tags" : [],
               "text" : "<a href=\"https://www.reddit.com/r/perl/comments/6rsref/parsing_csv_in_perl_6_has_become_a_lot_faster/\">comments</a>",
               "title" : "Parsing CSV in Perl 6 has become a lot faster over time ",
               "ts" : "2017.08",
               "url" : "http://tux.nl/Talks/CSV6/speed4.html"
            },
            {
               "author" : "",
               "tags" : [],
               "text" : "",
               "title" : "How many people plan to move to Perl 6?",
               "ts" : "2017.08.01",
               "url" : "https://www.reddit.com/r/perl/comments/6qsv6k/how_many_people_plan_to_move_to_perl_6/"
            },
            {
               "author" : "",
               "tags" : [],
               "text" : "",
               "title" : "The 3 most important things missing from Perl 6",
               "ts" : "2017.08.02",
               "url" : "https://www.reddit.com/r/perl/comments/6qvf55/the_3_most_important_things_missing_from_perl_6/"
            }
         ],
         "title" : "Perl 6"
      },
      {
         "entries" : [
            {
               "author" : "miguel_prz",
               "tags" : [],
               "text" : "<a href=\"http://niceperl.blogspot.com/2017/08/cxliv-cpan-great-modules-released-last.html\">Great modules released last week</a>;<br><a href=\"http://niceperl.blogspot.com/2017/08/cclxxvi-metacpan-weekly-report.html\">MetaCPAN weekly report</a>;<br><a href=\"http://niceperl.blogspot.com/2017/08/ccc-stackoverflow-perl-report.html\">StackOverflow Perl report</a>.",
               "title" : "NICEPERL's lists",
               "ts" : "2017.08.06",
               "url" : "http://niceperl.blogspot.com/"
            }
         ],
         "title" : "Weekly collections"
      },
      {
         "entries" : [
            {
               "author" : "dan_wright",
               "tags" : [],
               "text" : "I love transparency in finances of The Perl Foundation and the Perl events. It seems with the years smaller and smaller percentage of attendees were paying. After a peak of expenses in 2015, it seems the budgets is getting saner again. Oh and BTW the organizers are open for more volunteers to join them for the 2018 event!",
               "title" : "TPC::NA 2017 Finance Report",
               "ts" : "2017.08.03",
               "url" : "http://news.perlfoundation.org/2017/08/tpcna-2017-finance-report.html"
            }
         ],
         "title" : "Money Money Money"
      },
      {
         "entries" : [
            {
               "author" : "jim_brandt",
               "tags" : [],
               "text" : "17 years!",
               "title" : "Kurt DeMaagd Stepping Down from TPF Board",
               "ts" : "2017.08.04",
               "url" : "http://news.perlfoundation.org/2017/08/kurt-demaagd-stepping-down-fro.html"
            }
         ],
         "title" : "The Perl Foundation"
      },
      {
         "entries" : [
            {
               "text" : "This is a friendly, dynamic team based in Canary Wharf and for the first time the company is offering visa sponsorship for the right candidate. If you’ve got experience with Modern Perl this could be your opportunity to make the move to sunny London.",
               "title" : "Sponsorship opportunity available for mid-level or senior Perl developers in London",
               "url" : "https://perl.careers/jobs/sponsorship-opportunity-available-for-mid-level-or-senior-perl-developers-in-london/?utm_source=perlweekly&utm_campaign=perlweekly&utm_medium=perlweekly"
            },
            {
               "text" : "Ever find yourself wishing you could see meaningful impact on users from your work? Trapped in a company with long release cycles and dubious release dates? Wish your ideas for product improvement didn’t keep disappearing in to the Project Manager’s backlog?",
               "title" : "Do you love customers? Senior Perl Developer with a product focus, London",
               "url" : "https://perl.careers/jobs/do-you-love-customers-senior-perl-developer-with-a-product-focus-london/?utm_source=perlweekly&utm_campaign=perlweekly&utm_medium=perlweekly"
            },
            {
               "text" : "Do you know how to solve problems in terms of queues and caches? Does the idea of truly scaling your architecture on AWS excite you? Not fazed by designing your workloads to be distributed?",
               "title" : "Perl for High Performance; Senior Developer, West London",
               "url" : "https://perl.careers/jobs/perl-for-high-performance-senior-developer-west-london/?utm_source=perlweekly&utm_campaign=perlweekly&utm_medium=perlweekly"
            }
         ],
         "sponsor" : 1,
         "title" : "<a href=\"https://perl.careers/?utm_source=perlweekly&utm_campaign=perlweekly&utm_medium=perlweekly\">Perl Jobs by Perl Careers</a>"
      }
   ],
   "date" : "2017-08-07",
   "editor" : "gabor_szabo",
   "footer" : [],
   "header" : [
      "Hello there!",
      "If you are among the lucky 300 or so attending the conference in Amsterdam, then enjoy! We are looking forward to your reports!",
      "Tons of grant-related posts from TPF. It is great to see the frequent reports! Even if some are not exactly timed well :)",
      "There are also tons of Perl 6 related articles. Which reminds me that you can get the <a href=\"http://www.apress.com/us/book/9781484228982\">Perl 6 Fundamentals</a> book of Moritz Lenz both in e- and dead-tree version now.",
      "Enjoy your book and enjoy your week!"
   ],
   "subject" : "*Welcome to TPCiA - The Perl Conference in Amsterdam"
}
